{
  "type": "FeatureCollection",
  "metadata": {
    "generated": 1777623859000,
    "url": "https://earthquake.usgs.gov/earthquakes/feed/v1.0/summary/all_hour.geojson",
    "title": "USGS All Earthquakes, Past Hour",
    "status": 200,
    "api": "2.4.0",
    "count": 8
  },
  "features": [
    {
      "type": "Feature",
      "properties": {
        "mag": 4.9,
        "place": "20 km SE of Silver Springs, Nevada",
        "time": 1777623440000,
        "updated": 1777623838665,
        "tz": null,
        "url": "https://earthquake.usgs.gov/earthquakes/eventpage/ew1777623450",
        "detail": "https://earthquake.usgs.gov/earthquakes/feed/v1.0/detail/ew1777623450.geojson",
        "felt": 5,
        "cdi": 4.1,
        "mmi": null,
        "alert": null,
        "status": "automatic",
        "tsunami": 0,
        "sig": 371,
        "net": "ew",
        "code": "1777623450",
        "ids": ",ew1777623450,",
        "sources": ",ew,",
        "types": ",dyfi,origin,shake-alert,",
        "nst": 60,
        "dmin": null,
        "rms": null,
        "gap": null,
        "magType": "mw",
        "type": "earthquake",
        "title": "M 4.9 - 20 km SE of Silver Springs, Nevada"
      },
      "geometry": {
        "type": "Point",
        "coordinates": [
          -119.0565,
          39.2864,
          9
        ]
      },
      "id": "ew1777623450"
    },
    {
      "type": "Feature",
      "properties": {
        "mag": 3.1,
        "place": "54 km NW of Elfin Cove, Alaska",
        "time": 1777623038378,
        "updated": 1777623200839,
        "tz": null,
        "url": "https://earthquake.usgs.gov/earthquakes/eventpage/aka2026iogzpr",
        "detail": "https://earthquake.usgs.gov/earthquakes/feed/v1.0/detail/aka2026iogzpr.geojson",
        "felt": null,
        "cdi": null,
        "mmi": null,
        "alert": null,
        "status": "automatic",
        "tsunami": 0,
        "sig": 148,
        "net": "ak",
        "code": "a2026iogzpr",
        "ids": ",aka2026iogzpr,",
        "sources": ",ak,",
        "types": ",origin,phase-data,",
        "nst": 19,
        "dmin": 0.7,
        "rms": 1,
        "gap": 150,
        "magType": "ml",
        "type": "earthquake",
        "title": "M 3.1 - 54 km NW of Elfin Cove, Alaska"
      },
      "geometry": {
        "type": "Point",
        "coordinates": [
          -137.03,
          58.52,
          3.2
        ]
      },
      "id": "aka2026iogzpr"
    },
    {
      "type": "Feature",
      "properties": {
        "mag": 2.4,
        "place": "5 km W of Houston, Alaska",
        "time": 1777623022734,
        "updated": 1777623110706,
        "tz": null,
        "url": "https://earthquake.usgs.gov/earthquakes/eventpage/aka2026iogzjt",
        "detail": "https://earthquake.usgs.gov/earthquakes/feed/v1.0/detail/aka2026iogzjt.geojson",
        "felt": null,
        "cdi": null,
        "mmi": null,
        "alert": null,
        "status": "automatic",
        "tsunami": 0,
        "sig": 89,
        "net": "ak",
        "code": "a2026iogzjt",
        "ids": ",aka2026iogzjt,",
        "sources": ",ak,",
        "types": ",origin,phase-data,",
        "nst": 45,
        "dmin": 0.4,
        "rms": 0.8,
        "gap": 70,
        "magType": "ml",
        "type": "earthquake",
        "title": "M 2.4 - 5 km W of Houston, Alaska"
      },
      "geometry": {
        "type": "Point",
        "coordinates": [
          -149.915,
          61.637,
          26.9
        ]
      },
      "id": "aka2026iogzjt"
    },
    {
      "type": "Feature",
      "properties": {
        "mag": 0.49,
        "place": "18 km NNW of Borrego Springs, CA",
        "time": 1777622435450,
        "updated": 1777622645709,
        "tz": null,
        "url": "https://earthquake.usgs.gov/earthquakes/eventpage/ci41238631",
        "detail": "https://earthquake.usgs.gov/earthquakes/feed/v1.0/detail/ci41238631.geojson",
        "felt": null,
        "cdi": null,
        "mmi": null,
        "alert": null,
        "status": "automatic",
        "tsunami": 0,
        "sig": 4,
        "net": "ci",
        "code": "41238631",
        "ids": ",ci41238631,",
        "sources": ",ci,",
        "types": ",nearby-cities,origin,phase-data,scitech-link,",
        "nst": 30,
        "dmin": 0.1168,
        "rms": 0.15,
        "gap": 67,
        "magType": "ml",
        "type": "earthquake",
        "title": "M 0.5 - 18 km NNW of Borrego Springs, CA"
      },
      "geometry": {
        "type": "Point",
        "coordinates": [
          -116.437333333333,
          33.4095,
          14.31
        ]
      },
      "id": "ci41238631"
    },
    {
      "type": "Feature",
      "properties": {
        "mag": 0.78,
        "place": "5 km SW of Redlands, CA",
        "time": 1777622379670,
        "updated": 1777622584968,
        "tz": null,
        "url": "https://earthquake.usgs.gov/earthquakes/eventpage/ci41238623",
        "detail": "https://earthquake.usgs.gov/earthquakes/feed/v1.0/detail/ci41238623.geojson",
        "felt": null,
        "cdi": null,
        "mmi": null,
        "alert": null,
        "status": "automatic",
        "tsunami": 0,
        "sig": 9,
        "net": "ci",
        "code": "41238623",
        "ids": ",ci41238623,",
        "sources": ",ci,",
        "types": ",nearby-cities,origin,phase-data,scitech-link,",
        "nst": 52,
        "dmin": 0.07923,
        "rms": 0.21,
        "gap": 41,
        "magType": "ml",
        "type": "earthquake",
        "title": "M 0.8 - 5 km SW of Redlands, CA"
      },
      "geometry": {
        "type": "Point",
        "coordinates": [
          -117.213166666667,
          34.0193333333333,
          13.87
        ]
      },
      "id": "ci41238623"
    },
    {
      "type": "Feature",
      "properties": {
        "mag": 1.09,
        "place": "2 km ESE of The Geysers, CA",
        "time": 1777621763370,
        "updated": 1777621857344,
        "tz": null,
        "url": "https://earthquake.usgs.gov/earthquakes/eventpage/nc75354807",
        "detail": "https://earthquake.usgs.gov/earthquakes/feed/v1.0/detail/nc75354807.geojson",
        "felt": null,
        "cdi": null,
        "mmi": null,
        "alert": null,
        "status": "automatic",
        "tsunami": 0,
        "sig": 18,
        "net": "nc",
        "code": "75354807",
        "ids": ",nc75354807,",
        "sources": ",nc,",
        "types": ",nearby-cities,origin,phase-data,",
        "nst": 12,
        "dmin": 0.01304,
        "rms": 0.1,
        "gap": 98,
        "magType": "md",
        "type": "earthquake",
        "title": "M 1.1 - 2 km ESE of The Geysers, CA"
      },
      "geometry": {
        "type": "Point",
        "coordinates": [
          -122.731498718262,
          38.7708320617676,
          0.889999985694885
        ]
      },
      "id": "nc75354807"
    },
    {
      "type": "Feature",
      "properties": {
        "mag": 2,
        "place": "6 km E of Falls City, Texas",
        "time": 1777621428311,
        "updated": 1777622471640,
        "tz": null,
        "url": "https://earthquake.usgs.gov/earthquakes/eventpage/tx2026imwnhi",
        "detail": "https://earthquake.usgs.gov/earthquakes/feed/v1.0/detail/tx2026imwnhi.geojson",
        "felt": null,
        "cdi": null,
        "mmi": null,
        "alert": null,
        "status": "automatic",
        "tsunami": 0,
        "sig": 62,
        "net": "tx",
        "code": "2026imwnhi",
        "ids": ",tx2026imwnhi,",
        "sources": ",tx,",
        "types": ",origin,phase-data,",
        "nst": 13,
        "dmin": 0,
        "rms": 0.4,
        "gap": 65,
        "magType": "ml",
        "type": "earthquake",
        "title": "M 2.0 - 6 km E of Falls City, Texas"
      },
      "geometry": {
        "type": "Point",
        "coordinates": [
          -97.95,
          28.972,
          7.424
        ]
      },
      "id": "tx2026imwnhi"
    },
    {
      "type": "Feature",
      "properties": {
        "mag": 1.1,
        "place": "14 km NNW of Sand Springs, Texas",
        "time": 1777620647368,
        "updated": 1777622456544,
        "tz": null,
        "url": "https://earthquake.usgs.gov/earthquakes/eventpage/tx2026imwbzr",
        "detail": "https://earthquake.usgs.gov/earthquakes/feed/v1.0/detail/tx2026imwbzr.geojson",
        "felt": null,
        "cdi": null,
        "mmi": null,
        "alert": null,
        "status": "automatic",
        "tsunami": 0,
        "sig": 19,
        "net": "tx",
        "code": "2026imwbzr",
        "ids": ",tx2026imwbzr,",
        "sources": ",tx,",
        "types": ",origin,phase-data,",
        "nst": 10,
        "dmin": 0,
        "rms": 0.2,
        "gap": 76,
        "magType": "ml",
        "type": "earthquake",
        "title": "M 1.1 - 14 km NNW of Sand Springs, Texas"
      },
      "geometry": {
        "type": "Point",
        "coordinates": [
          -101.394,
          32.405,
          3.7627
        ]
      },
      "id": "tx2026imwbzr"
    }
  ],
  "bbox": [
    -149.915,
    28.972,
    0.88999998569489,
    -97.95,
    61.637,
    26.9
  ]
}
