{
  "type": "FeatureCollection",
  "metadata": {
    "generated": 1758868991000,
    "url": "https://earthquake.usgs.gov/earthquakes/feed/v1.0/summary/all_hour.geojson",
    "title": "USGS All Earthquakes, Past Hour",
    "status": 200,
    "api": "2.2.0",
    "count": 8
  },
  "features": [
    {
      "type": "Feature",
      "properties": {
        "mag": 2.6,
        "place": "17 km NNW of Toyah, Texas",
        "time": 1758868743210,
        "updated": 1758868963649,
        "tz": null,
        "url": "https://earthquake.usgs.gov/earthquakes/eventpage/tx2025syltpk",
        "detail": "https://earthquake.usgs.gov/earthquakes/feed/v1.0/detail/tx2025syltpk.geojson",
        "felt": null,
        "cdi": null,
        "mmi": null,
        "alert": null,
        "status": "automatic",
        "tsunami": 0,
        "sig": 104,
        "net": "tx",
        "code": "2025syltpk",
        "ids": ",tx2025syltpk,",
        "sources": ",tx,",
        "types": ",origin,",
        "nst": 32,
        "dmin": 0.1,
        "rms": 0.4,
        "gap": 60,
        "magType": "ml",
        "type": "earthquake",
        "title": "M 2.6 - 17 km NNW of Toyah, Texas"
      },
      "geometry": {
        "type": "Point",
        "coordinates": [
          -103.831,
          31.469,
          7.1062
        ]
      },
      "id": "tx2025syltpk"
    },
    {
      "type": "Feature",
      "properties": {
        "mag": 2,
        "place": "49 km NW of Toyah, Texas",
        "time": 1758868716809,
        "updated": 1758868914639,
        "tz": null,
        "url": "https://earthquake.usgs.gov/earthquakes/eventpage/tx2025sylvjj",
        "detail": "https://earthquake.usgs.gov/earthquakes/feed/v1.0/detail/tx2025sylvjj.geojson",
        "felt": null,
        "cdi": null,
        "mmi": null,
        "alert": null,
        "status": "automatic",
        "tsunami": 0,
        "sig": 62,
        "net": "tx",
        "code": "2025sylvjj",
        "ids": ",tx2025sylvjj,",
        "sources": ",tx,",
        "types": ",origin,phase-data,",
        "nst": 8,
        "dmin": 0.1,
        "rms": 0.3,
        "gap": 184,
        "magType": "ml",
        "type": "earthquake",
        "title": "M 2.0 - 49 km NW of Toyah, Texas"
      },
      "geometry": {
        "type": "Point",
        "coordinates": [
          -104.211,
          31.576,
          2.8656
        ]
      },
      "id": "tx2025sylvjj"
    },
    {
      "type": "Feature",
      "properties": {
        "mag": 1.6,
        "place": "18 km ENE of Walker Lake, Nevada",
        "time": 1758868280655,
        "updated": 1758868440294,
        "tz": null,
        "url": "https://earthquake.usgs.gov/earthquakes/eventpage/nn00905036",
        "detail": "https://earthquake.usgs.gov/earthquakes/feed/v1.0/detail/nn00905036.geojson",
        "felt": null,
        "cdi": null,
        "mmi": null,
        "alert": null,
        "status": "automatic",
        "tsunami": 0,
        "sig": 39,
        "net": "nn",
        "code": "00905036",
        "ids": ",nn00905036,",
        "sources": ",nn,",
        "types": ",origin,phase-data,",
        "nst": 14,
        "dmin": 0.469,
        "rms": 0.187,
        "gap": 85.92999999999999,
        "magType": "ml",
        "type": "earthquake",
        "title": "M 1.6 - 18 km ENE of Walker Lake, Nevada"
      },
      "geometry": {
        "type": "Point",
        "coordinates": [
          -118.5562,
          38.7182,
          0
        ]
      },
      "id": "nn00905036"
    },
    {
      "type": "Feature",
      "properties": {
        "mag": 1.5,
        "place": "3 km NNE of Houston, Alaska",
        "time": 1758868172780,
        "updated": 1758868270149,
        "tz": null,
        "url": "https://earthquake.usgs.gov/earthquakes/eventpage/ak025cczb8ri",
        "detail": "https://earthquake.usgs.gov/earthquakes/feed/v1.0/detail/ak025cczb8ri.geojson",
        "felt": null,
        "cdi": null,
        "mmi": null,
        "alert": null,
        "status": "automatic",
        "tsunami": 0,
        "sig": 35,
        "net": "ak",
        "code": "025cczb8ri",
        "ids": ",ak025cczb8ri,",
        "sources": ",ak,",
        "types": ",origin,phase-data,",
        "nst": null,
        "dmin": null,
        "rms": 0.4,
        "gap": null,
        "magType": "ml",
        "type": "earthquake",
        "title": "M 1.5 - 3 km NNE of Houston, Alaska"
      },
      "geometry": {
        "type": "Point",
        "coordinates": [
          -149.7836,
          61.6574,
          48.5
        ]
      },
      "id": "ak025cczb8ri"
    },
    {
      "type": "Feature",
      "properties": {
        "mag": 2.1,
        "place": "17 km NNW of Toyah, Texas",
        "time": 1758867125008,
        "updated": 1758867387477,
        "tz": null,
        "url": "https://earthquake.usgs.gov/earthquakes/eventpage/tx2025sykyma",
        "detail": "https://earthquake.usgs.gov/earthquakes/feed/v1.0/detail/tx2025sykyma.geojson",
        "felt": null,
        "cdi": null,
        "mmi": null,
        "alert": null,
        "status": "automatic",
        "tsunami": 0,
        "sig": 68,
        "net": "tx",
        "code": "2025sykyma",
        "ids": ",tx2025sykyma,",
        "sources": ",tx,",
        "types": ",origin,phase-data,",
        "nst": 35,
        "dmin": 0.1,
        "rms": 0.4,
        "gap": 61,
        "magType": "ml",
        "type": "earthquake",
        "title": "M 2.1 - 17 km NNW of Toyah, Texas"
      },
      "geometry": {
        "type": "Point",
        "coordinates": [
          -103.83,
          31.471,
          7.7559
        ]
      },
      "id": "tx2025sykyma"
    },
    {
      "type": "Feature",
      "properties": {
        "mag": 3.8,
        "place": "18 km ENE of Walker Lake, Nevada",
        "time": 1758866702057,
        "updated": 1758868407347,
        "tz": null,
        "url": "https://earthquake.usgs.gov/earthquakes/eventpage/us6000rd1k",
        "detail": "https://earthquake.usgs.gov/earthquakes/feed/v1.0/detail/us6000rd1k.geojson",
        "felt": 5,
        "cdi": 3.5,
        "mmi": 3.905,
        "alert": null,
        "status": "reviewed",
        "tsunami": 0,
        "sig": 224,
        "net": "us",
        "code": "6000rd1k",
        "ids": ",us6000rd1k,",
        "sources": ",us,",
        "types": ",dyfi,moment-tensor,origin,phase-data,shakemap,",
        "nst": 51,
        "dmin": 0.339,
        "rms": 0.86,
        "gap": 27,
        "magType": "mwr",
        "type": "earthquake",
        "title": "M 3.8 - 18 km ENE of Walker Lake, Nevada"
      },
      "geometry": {
        "type": "Point",
        "coordinates": [
          -118.551,
          38.7075,
          10
        ]
      },
      "id": "us6000rd1k"
    },
    {
      "type": "Feature",
      "properties": {
        "mag": 1.9,
        "place": "7 km WNW of Point MacKenzie, Alaska",
        "time": 1758866282597,
        "updated": 1758866364193,
        "tz": null,
        "url": "https://earthquake.usgs.gov/earthquakes/eventpage/ak025ccyvylf",
        "detail": "https://earthquake.usgs.gov/earthquakes/feed/v1.0/detail/ak025ccyvylf.geojson",
        "felt": null,
        "cdi": null,
        "mmi": null,
        "alert": null,
        "status": "automatic",
        "tsunami": 0,
        "sig": 56,
        "net": "ak",
        "code": "025ccyvylf",
        "ids": ",ak025ccyvylf,",
        "sources": ",ak,",
        "types": ",origin,phase-data,",
        "nst": null,
        "dmin": null,
        "rms": 0.32,
        "gap": null,
        "magType": "ml",
        "type": "earthquake",
        "title": "M 1.9 - 7 km WNW of Point MacKenzie, Alaska"
      },
      "geometry": {
        "type": "Point",
        "coordinates": [
          -150.1005,
          61.3891,
          34.5
        ]
      },
      "id": "ak025ccyvylf"
    },
    {
      "type": "Feature",
      "properties": {
        "mag": 1.58,
        "place": "7 km NW of The Geysers, CA",
        "time": 1758866206050,
        "updated": 1758867738011,
        "tz": null,
        "url": "https://earthquake.usgs.gov/earthquakes/eventpage/nc75242192",
        "detail": "https://earthquake.usgs.gov/earthquakes/feed/v1.0/detail/nc75242192.geojson",
        "felt": 1,
        "cdi": 2,
        "mmi": null,
        "alert": null,
        "status": "automatic",
        "tsunami": 0,
        "sig": 39,
        "net": "nc",
        "code": "75242192",
        "ids": ",nc75242192,",
        "sources": ",nc,",
        "types": ",dyfi,nearby-cities,origin,phase-data,scitech-link,",
        "nst": 27,
        "dmin": 0.005318,
        "rms": 0.03,
        "gap": 47,
        "magType": "md",
        "type": "earthquake",
        "title": "M 1.6 - 7 km NW of The Geysers, CA"
      },
      "geometry": {
        "type": "Point",
        "coordinates": [
          -122.828498840332,
          38.8141670227051,
          1.04999995231628
        ]
      },
      "id": "nc75242192"
    }
  ],
  "bbox": [
    -150.1005,
    31.469,
    0,
    -103.83,
    61.6574,
    48.5
  ]
}
