{
  "type": "FeatureCollection",
  "metadata": {
    "generated": 1770362015000,
    "url": "https://earthquake.usgs.gov/earthquakes/feed/v1.0/summary/all_hour.geojson",
    "title": "USGS All Earthquakes, Past Hour",
    "status": 200,
    "api": "1.14.1",
    "count": 2
  },
  "features": [
    {
      "type": "Feature",
      "properties": {
        "mag": 1.22,
        "place": "6 km W of Cobb, CA",
        "time": 1770361840210,
        "updated": 1770361934968,
        "tz": null,
        "url": "https://earthquake.usgs.gov/earthquakes/eventpage/nc75309397",
        "detail": "https://earthquake.usgs.gov/earthquakes/feed/v1.0/detail/nc75309397.geojson",
        "felt": null,
        "cdi": null,
        "mmi": null,
        "alert": null,
        "status": "automatic",
        "tsunami": 0,
        "sig": 23,
        "net": "nc",
        "code": "75309397",
        "ids": ",nc75309397,",
        "sources": ",nc,",
        "types": ",nearby-cities,origin,phase-data,",
        "nst": 17,
        "dmin": 0.006136,
        "rms": 0.02,
        "gap": 65,
        "magType": "md",
        "type": "earthquake",
        "title": "M 1.2 - 6 km W of Cobb, CA"
      },
      "geometry": {
        "type": "Point",
        "coordinates": [
          -122.792503356934,
          38.8325004577637,
          1.79999995231628
        ]
      },
      "id": "nc75309397"
    },
    {
      "type": "Feature",
      "properties": {
        "mag": 1.36,
        "place": "13 km SSW of Arvin, CA",
        "time": 1770360879530,
        "updated": 1770361100080,
        "tz": null,
        "url": "https://earthquake.usgs.gov/earthquakes/eventpage/ci41392680",
        "detail": "https://earthquake.usgs.gov/earthquakes/feed/v1.0/detail/ci41392680.geojson",
        "felt": null,
        "cdi": null,
        "mmi": null,
        "alert": null,
        "status": "automatic",
        "tsunami": 0,
        "sig": 28,
        "net": "ci",
        "code": "41392680",
        "ids": ",ci41392680,",
        "sources": ",ci,",
        "types": ",nearby-cities,origin,phase-data,scitech-link,",
        "nst": 47,
        "dmin": 0.1399,
        "rms": 0.23,
        "gap": 23,
        "magType": "ml",
        "type": "earthquake",
        "title": "M 1.4 - 13 km SSW of Arvin, CA"
      },
      "geometry": {
        "type": "Point",
        "coordinates": [
          -118.889333333333,
          35.1001666666667,
          15.11
        ]
      },
      "id": "ci41392680"
    }
  ],
  "bbox": [
    -122.79250335693,
    35.100166666667,
    1.7999999523163,
    -118.88933333333,
    38.832500457764,
    15.11
  ]
}
