{
  "type": "FeatureCollection",
  "metadata": {
    "generated": 1752562084000,
    "url": "https://earthquake.usgs.gov/earthquakes/feed/v1.0/summary/all_hour.geojson",
    "title": "USGS All Earthquakes, Past Hour",
    "status": 200,
    "api": "1.14.1",
    "count": 16
  },
  "features": [
    {
      "type": "Feature",
      "properties": {
        "mag": 1.63,
        "place": "12 km SSE of Petrolia, CA",
        "time": 1752561534310,
        "updated": 1752561631843,
        "tz": null,
        "url": "https://earthquake.usgs.gov/earthquakes/eventpage/nc75210092",
        "detail": "https://earthquake.usgs.gov/earthquakes/feed/v1.0/detail/nc75210092.geojson",
        "felt": null,
        "cdi": null,
        "mmi": null,
        "alert": null,
        "status": "automatic",
        "tsunami": 0,
        "sig": 41,
        "net": "nc",
        "code": "75210092",
        "ids": ",nc75210092,",
        "sources": ",nc,",
        "types": ",nearby-cities,origin,phase-data,",
        "nst": 8,
        "dmin": 0.03063,
        "rms": 0.02,
        "gap": 190,
        "magType": "md",
        "type": "earthquake",
        "title": "M 1.6 - 12 km SSE of Petrolia, CA"
      },
      "geometry": {
        "type": "Point",
        "coordinates": [
          -124.203498840332,
          40.2333335876465,
          13.4499998092651
        ]
      },
      "id": "nc75210092"
    },
    {
      "type": "Feature",
      "properties": {
        "mag": 0.8,
        "place": "7 km WSW of Palomar Observatory, CA",
        "time": 1752561528790,
        "updated": 1752561885318,
        "tz": null,
        "url": "https://earthquake.usgs.gov/earthquakes/eventpage/ci41022935",
        "detail": "https://earthquake.usgs.gov/earthquakes/feed/v1.0/detail/ci41022935.geojson",
        "felt": null,
        "cdi": null,
        "mmi": null,
        "alert": null,
        "status": "automatic",
        "tsunami": 0,
        "sig": 10,
        "net": "ci",
        "code": "41022935",
        "ids": ",ci41022935,",
        "sources": ",ci,",
        "types": ",nearby-cities,origin,phase-data,scitech-link,",
        "nst": 7,
        "dmin": 0.1977,
        "rms": 0.32,
        "gap": 179,
        "magType": "ml",
        "type": "earthquake",
        "title": "M 0.8 - 7 km WSW of Palomar Observatory, CA"
      },
      "geometry": {
        "type": "Point",
        "coordinates": [
          -116.941,
          33.3391667,
          26.69
        ]
      },
      "id": "ci41022935"
    },
    {
      "type": "Feature",
      "properties": {
        "mag": 0.76,
        "place": "9 km WNW of Palomar Observatory, CA",
        "time": 1752561504640,
        "updated": 1752561837741,
        "tz": null,
        "url": "https://earthquake.usgs.gov/earthquakes/eventpage/ci41022927",
        "detail": "https://earthquake.usgs.gov/earthquakes/feed/v1.0/detail/ci41022927.geojson",
        "felt": null,
        "cdi": null,
        "mmi": null,
        "alert": null,
        "status": "automatic",
        "tsunami": 0,
        "sig": 9,
        "net": "ci",
        "code": "41022927",
        "ids": ",ci41022927,",
        "sources": ",ci,",
        "types": ",nearby-cities,origin,phase-data,scitech-link,",
        "nst": 6,
        "dmin": 0.1763,
        "rms": 0.22,
        "gap": 166,
        "magType": "ml",
        "type": "earthquake",
        "title": "M 0.8 - 9 km WNW of Palomar Observatory, CA"
      },
      "geometry": {
        "type": "Point",
        "coordinates": [
          -116.959,
          33.3795,
          13.52
        ]
      },
      "id": "ci41022927"
    },
    {
      "type": "Feature",
      "properties": {
        "mag": 1.3,
        "place": "47 km SSE of Denali National Park, Alaska",
        "time": 1752561482913,
        "updated": 1752561665300,
        "tz": null,
        "url": "https://earthquake.usgs.gov/earthquakes/eventpage/ak0259094rur",
        "detail": "https://earthquake.usgs.gov/earthquakes/feed/v1.0/detail/ak0259094rur.geojson",
        "felt": null,
        "cdi": null,
        "mmi": null,
        "alert": null,
        "status": "automatic",
        "tsunami": 0,
        "sig": 26,
        "net": "ak",
        "code": "0259094rur",
        "ids": ",ak0259094rur,",
        "sources": ",ak,",
        "types": ",origin,phase-data,",
        "nst": null,
        "dmin": null,
        "rms": 1.34,
        "gap": null,
        "magType": "ml",
        "type": "earthquake",
        "title": "M 1.3 - 47 km SSE of Denali National Park, Alaska"
      },
      "geometry": {
        "type": "Point",
        "coordinates": [
          -151.4672,
          63.1307,
          0
        ]
      },
      "id": "ak0259094rur"
    },
    {
      "type": "Feature",
      "properties": {
        "mag": 1.22,
        "place": "6 km WSW of Ojai, CA",
        "time": 1752560977100,
        "updated": 1752561180886,
        "tz": null,
        "url": "https://earthquake.usgs.gov/earthquakes/eventpage/ci41022903",
        "detail": "https://earthquake.usgs.gov/earthquakes/feed/v1.0/detail/ci41022903.geojson",
        "felt": null,
        "cdi": null,
        "mmi": null,
        "alert": null,
        "status": "automatic",
        "tsunami": 0,
        "sig": 23,
        "net": "ci",
        "code": "41022903",
        "ids": ",ci41022903,",
        "sources": ",ci,",
        "types": ",nearby-cities,origin,phase-data,scitech-link,",
        "nst": 30,
        "dmin": 0.03952,
        "rms": 0.24,
        "gap": 35,
        "magType": "ml",
        "type": "earthquake",
        "title": "M 1.2 - 6 km WSW of Ojai, CA"
      },
      "geometry": {
        "type": "Point",
        "coordinates": [
          -119.309,
          34.4356667,
          9.45
        ]
      },
      "id": "ci41022903"
    },
    {
      "type": "Feature",
      "properties": {
        "mag": 1.1,
        "place": "59 km NE of Whittier, Alaska",
        "time": 1752560842855,
        "updated": 1752560943150,
        "tz": null,
        "url": "https://earthquake.usgs.gov/earthquakes/eventpage/ak0259092gil",
        "detail": "https://earthquake.usgs.gov/earthquakes/feed/v1.0/detail/ak0259092gil.geojson",
        "felt": null,
        "cdi": null,
        "mmi": null,
        "alert": null,
        "status": "automatic",
        "tsunami": 0,
        "sig": 19,
        "net": "ak",
        "code": "0259092gil",
        "ids": ",ak0259092gil,",
        "sources": ",ak,",
        "types": ",origin,phase-data,",
        "nst": null,
        "dmin": null,
        "rms": 1.35,
        "gap": null,
        "magType": "ml",
        "type": "earthquake",
        "title": "M 1.1 - 59 km NE of Whittier, Alaska"
      },
      "geometry": {
        "type": "Point",
        "coordinates": [
          -147.8594,
          61.1309,
          5.9
        ]
      },
      "id": "ak0259092gil"
    },
    {
      "type": "Feature",
      "properties": {
        "mag": 2.01,
        "place": "5 km ENE of Calumet, Oklahoma",
        "time": 1752560842458,
        "updated": 1752561056311,
        "tz": null,
        "url": "https://earthquake.usgs.gov/earthquakes/eventpage/ok2025nstw",
        "detail": "https://earthquake.usgs.gov/earthquakes/feed/v1.0/detail/ok2025nstw.geojson",
        "felt": null,
        "cdi": null,
        "mmi": null,
        "alert": null,
        "status": "automatic",
        "tsunami": 0,
        "sig": 62,
        "net": "ok",
        "code": "2025nstw",
        "ids": ",ok2025nstw,",
        "sources": ",ok,",
        "types": ",origin,phase-data,",
        "nst": 10,
        "dmin": 0.1462335587,
        "rms": 1.021125006,
        "gap": 107.5925064,
        "magType": "ml",
        "type": "earthquake",
        "title": "M 2.0 - 5 km ENE of Calumet, Oklahoma"
      },
      "geometry": {
        "type": "Point",
        "coordinates": [
          -98.05535889,
          35.61439896,
          7.106415272
        ]
      },
      "id": "ok2025nstw"
    },
    {
      "type": "Feature",
      "properties": {
        "mag": 0.89,
        "place": "18 km WSW of Johannesburg, CA",
        "time": 1752560810610,
        "updated": 1752561020811,
        "tz": null,
        "url": "https://earthquake.usgs.gov/earthquakes/eventpage/ci41022895",
        "detail": "https://earthquake.usgs.gov/earthquakes/feed/v1.0/detail/ci41022895.geojson",
        "felt": null,
        "cdi": null,
        "mmi": null,
        "alert": null,
        "status": "automatic",
        "tsunami": 0,
        "sig": 12,
        "net": "ci",
        "code": "41022895",
        "ids": ",ci41022895,",
        "sources": ",ci,",
        "types": ",nearby-cities,origin,phase-data,scitech-link,",
        "nst": 25,
        "dmin": 0.04941,
        "rms": 0.17,
        "gap": 85,
        "magType": "ml",
        "type": "earthquake",
        "title": "M 0.9 - 18 km WSW of Johannesburg, CA"
      },
      "geometry": {
        "type": "Point",
        "coordinates": [
          -117.8226667,
          35.3131667,
          9.57
        ]
      },
      "id": "ci41022895"
    },
    {
      "type": "Feature",
      "properties": {
        "mag": 2,
        "place": "75 km WNW of Tyonek, Alaska",
        "time": 1752560710287,
        "updated": 1752560828337,
        "tz": null,
        "url": "https://earthquake.usgs.gov/earthquakes/eventpage/ak0259092044",
        "detail": "https://earthquake.usgs.gov/earthquakes/feed/v1.0/detail/ak0259092044.geojson",
        "felt": null,
        "cdi": null,
        "mmi": null,
        "alert": null,
        "status": "automatic",
        "tsunami": 0,
        "sig": 62,
        "net": "ak",
        "code": "0259092044",
        "ids": ",ak0259092044,",
        "sources": ",ak,",
        "types": ",origin,phase-data,",
        "nst": null,
        "dmin": null,
        "rms": 0.75,
        "gap": null,
        "magType": "ml",
        "type": "earthquake",
        "title": "M 2.0 - 75 km WNW of Tyonek, Alaska"
      },
      "geometry": {
        "type": "Point",
        "coordinates": [
          -152.4417,
          61.31,
          0
        ]
      },
      "id": "ak0259092044"
    },
    {
      "type": "Feature",
      "properties": {
        "mag": 1.3,
        "place": "17 km NNW of Westbrook, Texas",
        "time": 1752560706123,
        "updated": 1752560890441,
        "tz": null,
        "url": "https://earthquake.usgs.gov/earthquakes/eventpage/tx2025nuljlw",
        "detail": "https://earthquake.usgs.gov/earthquakes/feed/v1.0/detail/tx2025nuljlw.geojson",
        "felt": null,
        "cdi": null,
        "mmi": null,
        "alert": null,
        "status": "automatic",
        "tsunami": 0,
        "sig": 26,
        "net": "tx",
        "code": "2025nuljlw",
        "ids": ",tx2025nuljlw,",
        "sources": ",tx,",
        "types": ",origin,phase-data,",
        "nst": 12,
        "dmin": 0.1,
        "rms": 0.3,
        "gap": 139,
        "magType": "ml",
        "type": "earthquake",
        "title": "M 1.3 - 17 km NNW of Westbrook, Texas"
      },
      "geometry": {
        "type": "Point",
        "coordinates": [
          -101.084,
          32.497,
          3.73
        ]
      },
      "id": "tx2025nuljlw"
    },
    {
      "type": "Feature",
      "properties": {
        "mag": 1.4,
        "place": "79 km WNW of Tyonek, Alaska",
        "time": 1752560525767,
        "updated": 1752560601527,
        "tz": null,
        "url": "https://earthquake.usgs.gov/earthquakes/eventpage/ak0259091cm8",
        "detail": "https://earthquake.usgs.gov/earthquakes/feed/v1.0/detail/ak0259091cm8.geojson",
        "felt": null,
        "cdi": null,
        "mmi": null,
        "alert": null,
        "status": "automatic",
        "tsunami": 0,
        "sig": 30,
        "net": "ak",
        "code": "0259091cm8",
        "ids": ",ak0259091cm8,",
        "sources": ",ak,",
        "types": ",origin,phase-data,",
        "nst": null,
        "dmin": null,
        "rms": 0.83,
        "gap": null,
        "magType": "ml",
        "type": "earthquake",
        "title": "M 1.4 - 79 km WNW of Tyonek, Alaska"
      },
      "geometry": {
        "type": "Point",
        "coordinates": [
          -152.5238,
          61.3044,
          7.3
        ]
      },
      "id": "ak0259091cm8"
    },
    {
      "type": "Feature",
      "properties": {
        "mag": 1.35,
        "place": "14 km ENE of Indio, CA",
        "time": 1752560319560,
        "updated": 1752560978830,
        "tz": null,
        "url": "https://earthquake.usgs.gov/earthquakes/eventpage/ci41022887",
        "detail": "https://earthquake.usgs.gov/earthquakes/feed/v1.0/detail/ci41022887.geojson",
        "felt": null,
        "cdi": null,
        "mmi": null,
        "alert": null,
        "status": "automatic",
        "tsunami": 0,
        "sig": 28,
        "net": "ci",
        "code": "41022887",
        "ids": ",ci41022887,",
        "sources": ",ci,",
        "types": ",focal-mechanism,nearby-cities,origin,phase-data,scitech-link,",
        "nst": 52,
        "dmin": 0.1167,
        "rms": 0.17,
        "gap": 38,
        "magType": "ml",
        "type": "earthquake",
        "title": "M 1.4 - 14 km ENE of Indio, CA"
      },
      "geometry": {
        "type": "Point",
        "coordinates": [
          -116.0816667,
          33.7891667,
          1.54
        ]
      },
      "id": "ci41022887"
    },
    {
      "type": "Feature",
      "properties": {
        "mag": 0.360000014,
        "place": "22 km ENE of Ashford, Washington",
        "time": 1752559774820,
        "updated": 1752559864980,
        "tz": null,
        "url": "https://earthquake.usgs.gov/earthquakes/eventpage/uw62142942",
        "detail": "https://earthquake.usgs.gov/earthquakes/feed/v1.0/detail/uw62142942.geojson",
        "felt": null,
        "cdi": null,
        "mmi": null,
        "alert": null,
        "status": "automatic",
        "tsunami": 0,
        "sig": 2,
        "net": "uw",
        "code": "62142942",
        "ids": ",uw62142942,",
        "sources": ",uw,",
        "types": ",origin,phase-data,",
        "nst": 16,
        "dmin": null,
        "rms": 0.0299999993,
        "gap": 64,
        "magType": "md",
        "type": "earthquake",
        "title": "M 0.4 - 22 km ENE of Ashford, Washington"
      },
      "geometry": {
        "type": "Point",
        "coordinates": [
          -121.77083587646484,
          46.846168518066406,
          -1.19000005722046
        ]
      },
      "id": "uw62142942"
    },
    {
      "type": "Feature",
      "properties": {
        "mag": 1.4,
        "place": "76 km WNW of Tyonek, Alaska",
        "time": 1752559715416,
        "updated": 1752559790044,
        "tz": null,
        "url": "https://earthquake.usgs.gov/earthquakes/eventpage/ak025908yevp",
        "detail": "https://earthquake.usgs.gov/earthquakes/feed/v1.0/detail/ak025908yevp.geojson",
        "felt": null,
        "cdi": null,
        "mmi": null,
        "alert": null,
        "status": "automatic",
        "tsunami": 0,
        "sig": 30,
        "net": "ak",
        "code": "025908yevp",
        "ids": ",ak025908yevp,",
        "sources": ",ak,",
        "types": ",origin,phase-data,",
        "nst": null,
        "dmin": null,
        "rms": 0.19,
        "gap": null,
        "magType": "ml",
        "type": "earthquake",
        "title": "M 1.4 - 76 km WNW of Tyonek, Alaska"
      },
      "geometry": {
        "type": "Point",
        "coordinates": [
          -152.485,
          61.299,
          11.4
        ]
      },
      "id": "ak025908yevp"
    },
    {
      "type": "Feature",
      "properties": {
        "mag": 1.3,
        "place": "36 km SE of Malaga, New Mexico",
        "time": 1752559552577,
        "updated": 1752559900352,
        "tz": null,
        "url": "https://earthquake.usgs.gov/earthquakes/eventpage/tx2025nuksui",
        "detail": "https://earthquake.usgs.gov/earthquakes/feed/v1.0/detail/tx2025nuksui.geojson",
        "felt": null,
        "cdi": null,
        "mmi": null,
        "alert": null,
        "status": "automatic",
        "tsunami": 0,
        "sig": 26,
        "net": "tx",
        "code": "2025nuksui",
        "ids": ",tx2025nuksui,",
        "sources": ",tx,",
        "types": ",origin,phase-data,",
        "nst": 20,
        "dmin": 0,
        "rms": 0.4,
        "gap": 85,
        "magType": "ml",
        "type": "earthquake",
        "title": "M 1.3 - 36 km SE of Malaga, New Mexico"
      },
      "geometry": {
        "type": "Point",
        "coordinates": [
          -103.764,
          32.02,
          10.0131
        ]
      },
      "id": "tx2025nuksui"
    },
    {
      "type": "Feature",
      "properties": {
        "mag": 0.75,
        "place": "7 km NW of The Geysers, CA",
        "time": 1752559248680,
        "updated": 1752559347389,
        "tz": null,
        "url": "https://earthquake.usgs.gov/earthquakes/eventpage/nc75210087",
        "detail": "https://earthquake.usgs.gov/earthquakes/feed/v1.0/detail/nc75210087.geojson",
        "felt": null,
        "cdi": null,
        "mmi": null,
        "alert": null,
        "status": "automatic",
        "tsunami": 0,
        "sig": 9,
        "net": "nc",
        "code": "75210087",
        "ids": ",nc75210087,",
        "sources": ",nc,",
        "types": ",nearby-cities,origin,phase-data,",
        "nst": 7,
        "dmin": 0.01043,
        "rms": 0.01,
        "gap": 89,
        "magType": "md",
        "type": "earthquake",
        "title": "M 0.8 - 7 km NW of The Geysers, CA"
      },
      "geometry": {
        "type": "Point",
        "coordinates": [
          -122.823165893555,
          38.8183326721191,
          1.82000005245209
        ]
      },
      "id": "nc75210087"
    }
  ],
  "bbox": [
    -152.5238,
    32.02,
    -1.1900000572205,
    -98.05535889,
    63.1307,
    26.69
  ]
}
