{
  "type": "FeatureCollection",
  "metadata": {
    "generated": 1752302679000,
    "url": "https://earthquake.usgs.gov/earthquakes/feed/v1.0/summary/all_hour.geojson",
    "title": "USGS All Earthquakes, Past Hour",
    "status": 200,
    "api": "1.14.1",
    "count": 10
  },
  "features": [
    {
      "type": "Feature",
      "properties": {
        "mag": 1.3,
        "place": "7 km ENE of Mina, Nevada",
        "time": 1752302140423,
        "updated": 1752302329224,
        "tz": null,
        "url": "https://earthquake.usgs.gov/earthquakes/eventpage/nn00900448",
        "detail": "https://earthquake.usgs.gov/earthquakes/feed/v1.0/detail/nn00900448.geojson",
        "felt": null,
        "cdi": null,
        "mmi": null,
        "alert": null,
        "status": "automatic",
        "tsunami": 0,
        "sig": 26,
        "net": "nn",
        "code": "00900448",
        "ids": ",nn00900448,",
        "sources": ",nn,",
        "types": ",origin,phase-data,",
        "nst": 10,
        "dmin": 0.407,
        "rms": 0.2702,
        "gap": 102.38,
        "magType": "ml",
        "type": "earthquake",
        "title": "M 1.3 - 7 km ENE of Mina, Nevada"
      },
      "geometry": {
        "type": "Point",
        "coordinates": [
          -118.0346,
          38.4244,
          1.8
        ]
      },
      "id": "nn00900448"
    },
    {
      "type": "Feature",
      "properties": {
        "mag": 1.12,
        "place": "12 km WNW of Calipatria, CA",
        "time": 1752301654880,
        "updated": 1752301883464,
        "tz": null,
        "url": "https://earthquake.usgs.gov/earthquakes/eventpage/ci41020831",
        "detail": "https://earthquake.usgs.gov/earthquakes/feed/v1.0/detail/ci41020831.geojson",
        "felt": null,
        "cdi": null,
        "mmi": null,
        "alert": null,
        "status": "automatic",
        "tsunami": 0,
        "sig": 19,
        "net": "ci",
        "code": "41020831",
        "ids": ",ci41020831,",
        "sources": ",ci,",
        "types": ",nearby-cities,origin,phase-data,scitech-link,",
        "nst": 34,
        "dmin": 0.01772,
        "rms": 0.21,
        "gap": 59,
        "magType": "ml",
        "type": "earthquake",
        "title": "M 1.1 - 12 km WNW of Calipatria, CA"
      },
      "geometry": {
        "type": "Point",
        "coordinates": [
          -115.6348333,
          33.1686667,
          5.09
        ]
      },
      "id": "ci41020831"
    },
    {
      "type": "Feature",
      "properties": {
        "mag": 1,
        "place": "36 km SE of Tanana, Alaska",
        "time": 1752301309946,
        "updated": 1752301423862,
        "tz": null,
        "url": "https://earthquake.usgs.gov/earthquakes/eventpage/ak0258vaf6tu",
        "detail": "https://earthquake.usgs.gov/earthquakes/feed/v1.0/detail/ak0258vaf6tu.geojson",
        "felt": null,
        "cdi": null,
        "mmi": null,
        "alert": null,
        "status": "automatic",
        "tsunami": 0,
        "sig": 15,
        "net": "ak",
        "code": "0258vaf6tu",
        "ids": ",ak0258vaf6tu,",
        "sources": ",ak,",
        "types": ",origin,phase-data,",
        "nst": null,
        "dmin": null,
        "rms": 0.26,
        "gap": null,
        "magType": "ml",
        "type": "earthquake",
        "title": "M 1.0 - 36 km SE of Tanana, Alaska"
      },
      "geometry": {
        "type": "Point",
        "coordinates": [
          -151.5578,
          64.9238,
          13
        ]
      },
      "id": "ak0258vaf6tu"
    },
    {
      "type": "Feature",
      "properties": {
        "mag": 0.72,
        "place": "15 km ENE of Ridgecrest, CA",
        "time": 1752301093330,
        "updated": 1752301298746,
        "tz": null,
        "url": "https://earthquake.usgs.gov/earthquakes/eventpage/ci41020823",
        "detail": "https://earthquake.usgs.gov/earthquakes/feed/v1.0/detail/ci41020823.geojson",
        "felt": null,
        "cdi": null,
        "mmi": null,
        "alert": null,
        "status": "automatic",
        "tsunami": 0,
        "sig": 8,
        "net": "ci",
        "code": "41020823",
        "ids": ",ci41020823,",
        "sources": ",ci,",
        "types": ",nearby-cities,origin,phase-data,scitech-link,",
        "nst": 23,
        "dmin": 0.07693,
        "rms": 0.15,
        "gap": 58,
        "magType": "ml",
        "type": "earthquake",
        "title": "M 0.7 - 15 km ENE of Ridgecrest, CA"
      },
      "geometry": {
        "type": "Point",
        "coordinates": [
          -117.5181667,
          35.6666667,
          10.54
        ]
      },
      "id": "ci41020823"
    },
    {
      "type": "Feature",
      "properties": {
        "mag": 2.43,
        "place": "10 km NNW of Ferndale, CA",
        "time": 1752301019450,
        "updated": 1752301339375,
        "tz": null,
        "url": "https://earthquake.usgs.gov/earthquakes/eventpage/nc75208682",
        "detail": "https://earthquake.usgs.gov/earthquakes/feed/v1.0/detail/nc75208682.geojson",
        "felt": null,
        "cdi": null,
        "mmi": null,
        "alert": null,
        "status": "automatic",
        "tsunami": 0,
        "sig": 91,
        "net": "nc",
        "code": "75208682",
        "ids": ",nc75208682,",
        "sources": ",nc,",
        "types": ",nearby-cities,origin,phase-data,scitech-link,",
        "nst": 20,
        "dmin": 0.1424,
        "rms": 0.07,
        "gap": 201,
        "magType": "md",
        "type": "earthquake",
        "title": "M 2.4 - 10 km NNW of Ferndale, CA"
      },
      "geometry": {
        "type": "Point",
        "coordinates": [
          -124.336669921875,
          40.6438331604004,
          20.5900001525879
        ]
      },
      "id": "nc75208682"
    },
    {
      "type": "Feature",
      "properties": {
        "mag": 2.3,
        "place": "4 km NNE of Star Valley Ranch, Wyoming",
        "time": 1752300876257,
        "updated": 1752301821451,
        "tz": null,
        "url": "https://earthquake.usgs.gov/earthquakes/eventpage/us7000qc7w",
        "detail": "https://earthquake.usgs.gov/earthquakes/feed/v1.0/detail/us7000qc7w.geojson",
        "felt": 1,
        "cdi": 2.7,
        "mmi": null,
        "alert": null,
        "status": "reviewed",
        "tsunami": 0,
        "sig": 82,
        "net": "us",
        "code": "7000qc7w",
        "ids": ",us7000qc7w,",
        "sources": ",us,",
        "types": ",dyfi,origin,phase-data,",
        "nst": 35,
        "dmin": 0.27,
        "rms": 0.4,
        "gap": 73,
        "magType": "ml",
        "type": "earthquake",
        "title": "M 2.3 - 4 km NNE of Star Valley Ranch, Wyoming"
      },
      "geometry": {
        "type": "Point",
        "coordinates": [
          -110.9427,
          43.0089,
          5.265
        ]
      },
      "id": "us7000qc7w"
    },
    {
      "type": "Feature",
      "properties": {
        "mag": 1.02,
        "place": "9 km WNW of Cobb, CA",
        "time": 1752300523880,
        "updated": 1752300619217,
        "tz": null,
        "url": "https://earthquake.usgs.gov/earthquakes/eventpage/nc75208677",
        "detail": "https://earthquake.usgs.gov/earthquakes/feed/v1.0/detail/nc75208677.geojson",
        "felt": null,
        "cdi": null,
        "mmi": null,
        "alert": null,
        "status": "automatic",
        "tsunami": 0,
        "sig": 16,
        "net": "nc",
        "code": "75208677",
        "ids": ",nc75208677,",
        "sources": ",nc,",
        "types": ",nearby-cities,origin,phase-data,",
        "nst": 14,
        "dmin": 0.01042,
        "rms": 0.03,
        "gap": 82,
        "magType": "md",
        "type": "earthquake",
        "title": "M 1.0 - 9 km WNW of Cobb, CA"
      },
      "geometry": {
        "type": "Point",
        "coordinates": [
          -122.822166442871,
          38.8380012512207,
          0.109999999403954
        ]
      },
      "id": "nc75208677"
    },
    {
      "type": "Feature",
      "properties": {
        "mag": 0.26,
        "place": "1 km  of The Geysers, CA",
        "time": 1752300104420,
        "updated": 1752300199211,
        "tz": null,
        "url": "https://earthquake.usgs.gov/earthquakes/eventpage/nc75208672",
        "detail": "https://earthquake.usgs.gov/earthquakes/feed/v1.0/detail/nc75208672.geojson",
        "felt": null,
        "cdi": null,
        "mmi": null,
        "alert": null,
        "status": "automatic",
        "tsunami": 0,
        "sig": 1,
        "net": "nc",
        "code": "75208672",
        "ids": ",nc75208672,",
        "sources": ",nc,",
        "types": ",nearby-cities,origin,phase-data,",
        "nst": 8,
        "dmin": 0.0136,
        "rms": 0.02,
        "gap": 92,
        "magType": "md",
        "type": "earthquake",
        "title": "M 0.3 - 1 km  of The Geysers, CA"
      },
      "geometry": {
        "type": "Point",
        "coordinates": [
          -122.758666992188,
          38.7831649780273,
          2.42000007629395
        ]
      },
      "id": "nc75208672"
    },
    {
      "type": "Feature",
      "properties": {
        "mag": 0.96,
        "place": "9 km WNW of Cobb, CA",
        "time": 1752299570090,
        "updated": 1752299668955,
        "tz": null,
        "url": "https://earthquake.usgs.gov/earthquakes/eventpage/nc75208662",
        "detail": "https://earthquake.usgs.gov/earthquakes/feed/v1.0/detail/nc75208662.geojson",
        "felt": null,
        "cdi": null,
        "mmi": null,
        "alert": null,
        "status": "automatic",
        "tsunami": 0,
        "sig": 14,
        "net": "nc",
        "code": "75208662",
        "ids": ",nc75208662,",
        "sources": ",nc,",
        "types": ",nearby-cities,origin,phase-data,",
        "nst": 12,
        "dmin": 0.00873,
        "rms": 0.03,
        "gap": 94,
        "magType": "md",
        "type": "earthquake",
        "title": "M 1.0 - 9 km WNW of Cobb, CA"
      },
      "geometry": {
        "type": "Point",
        "coordinates": [
          -122.824333190918,
          38.839168548584,
          1.26999998092651
        ]
      },
      "id": "nc75208662"
    },
    {
      "type": "Feature",
      "properties": {
        "mag": 0.69,
        "place": "9 km WNW of Cobb, CA",
        "time": 1752299543500,
        "updated": 1752299639171,
        "tz": null,
        "url": "https://earthquake.usgs.gov/earthquakes/eventpage/nc75208657",
        "detail": "https://earthquake.usgs.gov/earthquakes/feed/v1.0/detail/nc75208657.geojson",
        "felt": null,
        "cdi": null,
        "mmi": null,
        "alert": null,
        "status": "automatic",
        "tsunami": 0,
        "sig": 7,
        "net": "nc",
        "code": "75208657",
        "ids": ",nc75208657,",
        "sources": ",nc,",
        "types": ",nearby-cities,origin,phase-data,",
        "nst": 11,
        "dmin": 0.01027,
        "rms": 0.01,
        "gap": 87,
        "magType": "md",
        "type": "earthquake",
        "title": "M 0.7 - 9 km WNW of Cobb, CA"
      },
      "geometry": {
        "type": "Point",
        "coordinates": [
          -122.822334289551,
          38.8385009765625,
          0.660000026226044
        ]
      },
      "id": "nc75208657"
    }
  ],
  "bbox": [
    -151.5578,
    33.1686667,
    0.10999999940395,
    -110.9427,
    64.9238,
    20.590000152588
  ]
}
