{
  "type": "FeatureCollection",
  "metadata": {
    "generated": 1761979269000,
    "url": "https://earthquake.usgs.gov/earthquakes/feed/v1.0/summary/all_hour.geojson",
    "title": "USGS All Earthquakes, Past Hour",
    "status": 200,
    "api": "1.14.1",
    "count": 7
  },
  "features": [
    {
      "type": "Feature",
      "properties": {
        "mag": 1.2,
        "place": "11 km NE of Yucaipa, CA",
        "time": 1761977989850,
        "updated": 1761978198570,
        "tz": null,
        "url": "https://earthquake.usgs.gov/earthquakes/eventpage/ci41323720",
        "detail": "https://earthquake.usgs.gov/earthquakes/feed/v1.0/detail/ci41323720.geojson",
        "felt": null,
        "cdi": null,
        "mmi": null,
        "alert": null,
        "status": "automatic",
        "tsunami": 0,
        "sig": 22,
        "net": "ci",
        "code": "41323720",
        "ids": ",ci41323720,",
        "sources": ",ci,",
        "types": ",nearby-cities,origin,phase-data,scitech-link,",
        "nst": 70,
        "dmin": 0.03817,
        "rms": 0.16,
        "gap": 23,
        "magType": "ml",
        "type": "earthquake",
        "title": "M 1.2 - 11 km NE of Yucaipa, CA"
      },
      "geometry": {
        "type": "Point",
        "coordinates": [
          -116.9738333,
          34.1151667,
          6.16
        ]
      },
      "id": "ci41323720"
    },
    {
      "type": "Feature",
      "properties": {
        "mag": 0.89,
        "place": "4 km NE of Riverside, CA",
        "time": 1761977984400,
        "updated": 1761978198325,
        "tz": null,
        "url": "https://earthquake.usgs.gov/earthquakes/eventpage/ci41323712",
        "detail": "https://earthquake.usgs.gov/earthquakes/feed/v1.0/detail/ci41323712.geojson",
        "felt": null,
        "cdi": null,
        "mmi": null,
        "alert": null,
        "status": "automatic",
        "tsunami": 0,
        "sig": 12,
        "net": "ci",
        "code": "41323712",
        "ids": ",ci41323712,",
        "sources": ",ci,",
        "types": ",nearby-cities,origin,phase-data,scitech-link,",
        "nst": 23,
        "dmin": 0.102,
        "rms": 0.35,
        "gap": 132,
        "magType": "ml",
        "type": "earthquake",
        "title": "M 0.9 - 4 km NE of Riverside, CA"
      },
      "geometry": {
        "type": "Point",
        "coordinates": [
          -117.364,
          33.969,
          11.54
        ]
      },
      "id": "ci41323712"
    },
    {
      "type": "Feature",
      "properties": {
        "mag": 2.2,
        "place": "7 km SE of Girdwood, Alaska",
        "time": 1761977740087,
        "updated": 1761977871207,
        "tz": null,
        "url": "https://earthquake.usgs.gov/earthquakes/eventpage/ak025e0ikr2w",
        "detail": "https://earthquake.usgs.gov/earthquakes/feed/v1.0/detail/ak025e0ikr2w.geojson",
        "felt": null,
        "cdi": null,
        "mmi": null,
        "alert": null,
        "status": "automatic",
        "tsunami": 0,
        "sig": 74,
        "net": "ak",
        "code": "025e0ikr2w",
        "ids": ",ak025e0ikr2w,",
        "sources": ",ak,",
        "types": ",origin,phase-data,",
        "nst": null,
        "dmin": null,
        "rms": 0.31,
        "gap": null,
        "magType": "ml",
        "type": "earthquake",
        "title": "M 2.2 - 7 km SE of Girdwood, Alaska"
      },
      "geometry": {
        "type": "Point",
        "coordinates": [
          -149.0689,
          60.8978,
          10.1
        ]
      },
      "id": "ak025e0ikr2w"
    },
    {
      "type": "Feature",
      "properties": {
        "mag": 2.5,
        "place": "39 km ESE of Fox River, Alaska",
        "time": 1761977135471,
        "updated": 1761977250162,
        "tz": null,
        "url": "https://earthquake.usgs.gov/earthquakes/eventpage/ak025e0iilkb",
        "detail": "https://earthquake.usgs.gov/earthquakes/feed/v1.0/detail/ak025e0iilkb.geojson",
        "felt": null,
        "cdi": null,
        "mmi": null,
        "alert": null,
        "status": "automatic",
        "tsunami": 0,
        "sig": 96,
        "net": "ak",
        "code": "025e0iilkb",
        "ids": ",ak025e0iilkb,",
        "sources": ",ak,",
        "types": ",origin,phase-data,",
        "nst": null,
        "dmin": null,
        "rms": 0.67,
        "gap": null,
        "magType": "ml",
        "type": "earthquake",
        "title": "M 2.5 - 39 km ESE of Fox River, Alaska"
      },
      "geometry": {
        "type": "Point",
        "coordinates": [
          -150.3491,
          59.6779,
          22.8
        ]
      },
      "id": "ak025e0iilkb"
    },
    {
      "type": "Feature",
      "properties": {
        "mag": 1.8,
        "place": "44 km SE of Denali National Park, Alaska",
        "time": 1761976313538,
        "updated": 1761976459806,
        "tz": null,
        "url": "https://earthquake.usgs.gov/earthquakes/eventpage/ak025e0i72ah",
        "detail": "https://earthquake.usgs.gov/earthquakes/feed/v1.0/detail/ak025e0i72ah.geojson",
        "felt": null,
        "cdi": null,
        "mmi": null,
        "alert": null,
        "status": "automatic",
        "tsunami": 0,
        "sig": 50,
        "net": "ak",
        "code": "025e0i72ah",
        "ids": ",ak025e0i72ah,",
        "sources": ",ak,",
        "types": ",origin,phase-data,",
        "nst": null,
        "dmin": null,
        "rms": 0.55,
        "gap": null,
        "magType": "ml",
        "type": "earthquake",
        "title": "M 1.8 - 44 km SE of Denali National Park, Alaska"
      },
      "geometry": {
        "type": "Point",
        "coordinates": [
          -151.1124,
          63.2526,
          0.8
        ]
      },
      "id": "ak025e0i72ah"
    },
    {
      "type": "Feature",
      "properties": {
        "mag": 0.9,
        "place": "5 km WNW of Cobb, CA",
        "time": 1761975965370,
        "updated": 1761978440194,
        "tz": null,
        "url": "https://earthquake.usgs.gov/earthquakes/eventpage/nc75257406",
        "detail": "https://earthquake.usgs.gov/earthquakes/feed/v1.0/detail/nc75257406.geojson",
        "felt": null,
        "cdi": null,
        "mmi": null,
        "alert": null,
        "status": "automatic",
        "tsunami": 0,
        "sig": 12,
        "net": "nc",
        "code": "75257406",
        "ids": ",nc75257406,",
        "sources": ",nc,",
        "types": ",nearby-cities,origin,phase-data,scitech-link,",
        "nst": 11,
        "dmin": 0.006503,
        "rms": 0.02,
        "gap": 69,
        "magType": "md",
        "type": "earthquake",
        "title": "M 0.9 - 5 km WNW of Cobb, CA"
      },
      "geometry": {
        "type": "Point",
        "coordinates": [
          -122.781829833984,
          38.8376655578613,
          2.03999996185303
        ]
      },
      "id": "nc75257406"
    },
    {
      "type": "Feature",
      "properties": {
        "mag": 1.03,
        "place": "5 km WNW of Cobb, CA",
        "time": 1761975838310,
        "updated": 1761977843114,
        "tz": null,
        "url": "https://earthquake.usgs.gov/earthquakes/eventpage/nc75257401",
        "detail": "https://earthquake.usgs.gov/earthquakes/feed/v1.0/detail/nc75257401.geojson",
        "felt": null,
        "cdi": null,
        "mmi": null,
        "alert": null,
        "status": "automatic",
        "tsunami": 0,
        "sig": 16,
        "net": "nc",
        "code": "75257401",
        "ids": ",nc75257401,",
        "sources": ",nc,",
        "types": ",nearby-cities,origin,phase-data,scitech-link,",
        "nst": 15,
        "dmin": 0.007492,
        "rms": 0.03,
        "gap": 76,
        "magType": "md",
        "type": "earthquake",
        "title": "M 1.0 - 5 km WNW of Cobb, CA"
      },
      "geometry": {
        "type": "Point",
        "coordinates": [
          -122.78133392334,
          38.8358345031738,
          1.97000002861023
        ]
      },
      "id": "nc75257401"
    }
  ],
  "bbox": [
    -151.1124,
    33.969,
    0.8,
    -116.9738333,
    63.2526,
    22.8
  ]
}
