{
  "type": "FeatureCollection",
  "metadata": {
    "generated": 1773558861000,
    "url": "https://earthquake.usgs.gov/earthquakes/feed/v1.0/summary/all_hour.geojson",
    "title": "USGS All Earthquakes, Past Hour",
    "status": 200,
    "api": "2.3.0",
    "count": 11
  },
  "features": [
    {
      "type": "Feature",
      "properties": {
        "mag": 1.51,
        "place": "4 km NW of Pittsburg, CA",
        "time": 1773558612480,
        "updated": 1773558710727,
        "tz": null,
        "url": "https://earthquake.usgs.gov/earthquakes/eventpage/nc75327637",
        "detail": "https://earthquake.usgs.gov/earthquakes/feed/v1.0/detail/nc75327637.geojson",
        "felt": null,
        "cdi": null,
        "mmi": null,
        "alert": null,
        "status": "automatic",
        "tsunami": 0,
        "sig": 35,
        "net": "nc",
        "code": "75327637",
        "ids": ",nc75327637,",
        "sources": ",nc,",
        "types": ",nearby-cities,origin,phase-data,",
        "nst": 8,
        "dmin": 0.08675,
        "rms": 0.02,
        "gap": 81,
        "magType": "md",
        "type": "earthquake",
        "title": "M 1.5 - 4 km NW of Pittsburg, CA"
      },
      "geometry": {
        "type": "Point",
        "coordinates": [
          -121.911003112793,
          38.0525016784668,
          17.0200004577637
        ]
      },
      "id": "nc75327637"
    },
    {
      "type": "Feature",
      "properties": {
        "mag": 1.3,
        "place": "96 km NW of Aleneva, Alaska",
        "time": 1773557969723,
        "updated": 1773558094442,
        "tz": null,
        "url": "https://earthquake.usgs.gov/earthquakes/eventpage/aka2026fenxtb",
        "detail": "https://earthquake.usgs.gov/earthquakes/feed/v1.0/detail/aka2026fenxtb.geojson",
        "felt": null,
        "cdi": null,
        "mmi": null,
        "alert": null,
        "status": "automatic",
        "tsunami": 0,
        "sig": 26,
        "net": "ak",
        "code": "a2026fenxtb",
        "ids": ",aka2026fenxtb,",
        "sources": ",ak,",
        "types": ",origin,phase-data,",
        "nst": 8,
        "dmin": 0.1,
        "rms": 0.3,
        "gap": 290,
        "magType": "ml",
        "type": "earthquake",
        "title": "M 1.3 - 96 km NW of Aleneva, Alaska"
      },
      "geometry": {
        "type": "Point",
        "coordinates": [
          -154.253,
          58.558,
          5
        ]
      },
      "id": "aka2026fenxtb"
    },
    {
      "type": "Feature",
      "properties": {
        "mag": 2.3,
        "place": "5 km NNW of Pittsburg, CA",
        "time": 1773557448100,
        "updated": 1773558442886,
        "tz": null,
        "url": "https://earthquake.usgs.gov/earthquakes/eventpage/nc75327632",
        "detail": "https://earthquake.usgs.gov/earthquakes/feed/v1.0/detail/nc75327632.geojson",
        "felt": null,
        "cdi": null,
        "mmi": null,
        "alert": null,
        "status": "automatic",
        "tsunami": 0,
        "sig": 81,
        "net": "nc",
        "code": "75327632",
        "ids": ",nc75327632,",
        "sources": ",nc,",
        "types": ",focal-mechanism,nearby-cities,origin,phase-data,scitech-link,",
        "nst": 45,
        "dmin": 0.09141,
        "rms": 0.25,
        "gap": 76,
        "magType": "md",
        "type": "earthquake",
        "title": "M 2.3 - 5 km NNW of Pittsburg, CA"
      },
      "geometry": {
        "type": "Point",
        "coordinates": [
          -121.910331726074,
          38.0643348693848,
          18.6900005340576
        ]
      },
      "id": "nc75327632"
    },
    {
      "type": "Feature",
      "properties": {
        "mag": 1.9,
        "place": "54 km NW of Toyah, Texas",
        "time": 1773557187662,
        "updated": 1773557447590,
        "tz": null,
        "url": "https://earthquake.usgs.gov/earthquakes/eventpage/tx2026fenmna",
        "detail": "https://earthquake.usgs.gov/earthquakes/feed/v1.0/detail/tx2026fenmna.geojson",
        "felt": null,
        "cdi": null,
        "mmi": null,
        "alert": null,
        "status": "automatic",
        "tsunami": 0,
        "sig": 56,
        "net": "tx",
        "code": "2026fenmna",
        "ids": ",tx2026fenmna,",
        "sources": ",tx,",
        "types": ",origin,phase-data,",
        "nst": 33,
        "dmin": 0.1,
        "rms": 0.4,
        "gap": 113,
        "magType": "ml",
        "type": "earthquake",
        "title": "M 1.9 - 54 km NW of Toyah, Texas"
      },
      "geometry": {
        "type": "Point",
        "coordinates": [
          -104.202,
          31.665,
          4.1493
        ]
      },
      "id": "tx2026fenmna"
    },
    {
      "type": "Feature",
      "properties": {
        "mag": 2.5,
        "place": "55 km NW of Toyah, Texas",
        "time": 1773557099675,
        "updated": 1773558476040,
        "tz": null,
        "url": "https://earthquake.usgs.gov/earthquakes/eventpage/tx2026fenktd",
        "detail": "https://earthquake.usgs.gov/earthquakes/feed/v1.0/detail/tx2026fenktd.geojson",
        "felt": null,
        "cdi": null,
        "mmi": null,
        "alert": null,
        "status": "automatic",
        "tsunami": 0,
        "sig": 96,
        "net": "tx",
        "code": "2026fenktd",
        "ids": ",us6000sgf3,tx2026fenktd,",
        "sources": ",us,tx,",
        "types": ",origin,phase-data,",
        "nst": 43,
        "dmin": 0.1,
        "rms": 0.4,
        "gap": 63,
        "magType": "ml",
        "type": "earthquake",
        "title": "M 2.5 - 55 km NW of Toyah, Texas"
      },
      "geometry": {
        "type": "Point",
        "coordinates": [
          -104.207,
          31.666,
          4.5417
        ]
      },
      "id": "tx2026fenktd"
    },
    {
      "type": "Feature",
      "properties": {
        "mag": 0.95,
        "place": "4 km W of Lake Henshaw, CA",
        "time": 1773556824340,
        "updated": 1773557032789,
        "tz": null,
        "url": "https://earthquake.usgs.gov/earthquakes/eventpage/ci41204455",
        "detail": "https://earthquake.usgs.gov/earthquakes/feed/v1.0/detail/ci41204455.geojson",
        "felt": null,
        "cdi": null,
        "mmi": null,
        "alert": null,
        "status": "automatic",
        "tsunami": 0,
        "sig": 14,
        "net": "ci",
        "code": "41204455",
        "ids": ",ci41204455,",
        "sources": ",ci,",
        "types": ",nearby-cities,origin,phase-data,scitech-link,",
        "nst": 59,
        "dmin": 0.04118,
        "rms": 0.19,
        "gap": 23,
        "magType": "ml",
        "type": "earthquake",
        "title": "M 1.0 - 4 km W of Lake Henshaw, CA"
      },
      "geometry": {
        "type": "Point",
        "coordinates": [
          -116.806333333333,
          33.2463333333333,
          10.1
        ]
      },
      "id": "ci41204455"
    },
    {
      "type": "Feature",
      "properties": {
        "mag": 2.11,
        "place": "59 km ENE of Tonopah, Nevada",
        "time": 1773556053007,
        "updated": 1773556234776,
        "tz": null,
        "url": "https://earthquake.usgs.gov/earthquakes/eventpage/nn00912698",
        "detail": "https://earthquake.usgs.gov/earthquakes/feed/v1.0/detail/nn00912698.geojson",
        "felt": null,
        "cdi": null,
        "mmi": null,
        "alert": null,
        "status": "automatic",
        "tsunami": 0,
        "sig": 68,
        "net": "nn",
        "code": "00912698",
        "ids": ",nn00912698,",
        "sources": ",nn,",
        "types": ",origin,phase-data,",
        "nst": 18,
        "dmin": 0.524,
        "rms": 0.2813,
        "gap": 215,
        "magType": "ml",
        "type": "earthquake",
        "title": "M 2.1 - 59 km ENE of Tonopah, Nevada"
      },
      "geometry": {
        "type": "Point",
        "coordinates": [
          -116.6054,
          38.2724,
          5.7486
        ]
      },
      "id": "nn00912698"
    },
    {
      "type": "Feature",
      "properties": {
        "mag": 1.48,
        "place": "54 km WSW of Rachel, Nevada",
        "time": 1773555887891,
        "updated": 1773556033101,
        "tz": null,
        "url": "https://earthquake.usgs.gov/earthquakes/eventpage/nn00912696",
        "detail": "https://earthquake.usgs.gov/earthquakes/feed/v1.0/detail/nn00912696.geojson",
        "felt": null,
        "cdi": null,
        "mmi": null,
        "alert": null,
        "status": "automatic",
        "tsunami": 0,
        "sig": 34,
        "net": "nn",
        "code": "00912696",
        "ids": ",nn00912696,",
        "sources": ",nn,",
        "types": ",origin,phase-data,",
        "nst": 15,
        "dmin": 0.332,
        "rms": 0.3828,
        "gap": 168,
        "magType": "ml",
        "type": "earthquake",
        "title": "M 1.5 - 54 km WSW of Rachel, Nevada"
      },
      "geometry": {
        "type": "Point",
        "coordinates": [
          -116.3473,
          37.5427,
          15.7841
        ]
      },
      "id": "nn00912696"
    },
    {
      "type": "Feature",
      "properties": {
        "mag": 2.09,
        "place": "2 km SSE of Santo Domingo, Puerto Rico",
        "time": 1773555703900,
        "updated": 1773556524990,
        "tz": null,
        "url": "https://earthquake.usgs.gov/earthquakes/eventpage/pr71509903",
        "detail": "https://earthquake.usgs.gov/earthquakes/feed/v1.0/detail/pr71509903.geojson",
        "felt": null,
        "cdi": null,
        "mmi": null,
        "alert": null,
        "status": "reviewed",
        "tsunami": 0,
        "sig": 67,
        "net": "pr",
        "code": "71509903",
        "ids": ",pr71509903,",
        "sources": ",pr,",
        "types": ",origin,phase-data,",
        "nst": 22,
        "dmin": 0.05125,
        "rms": 0.2,
        "gap": 113,
        "magType": "md",
        "type": "earthquake",
        "title": "M 2.1 - 2 km SSE of Santo Domingo, Puerto Rico"
      },
      "geometry": {
        "type": "Point",
        "coordinates": [
          -66.7433333333333,
          18.043,
          16.94
        ]
      },
      "id": "pr71509903"
    },
    {
      "type": "Feature",
      "properties": {
        "mag": 0.9,
        "place": "37 km NNE of Chickaloon, Alaska",
        "time": 1773555584721,
        "updated": 1773555670004,
        "tz": null,
        "url": "https://earthquake.usgs.gov/earthquakes/eventpage/aka2026fempmc",
        "detail": "https://earthquake.usgs.gov/earthquakes/feed/v1.0/detail/aka2026fempmc.geojson",
        "felt": null,
        "cdi": null,
        "mmi": null,
        "alert": null,
        "status": "automatic",
        "tsunami": 0,
        "sig": 12,
        "net": "ak",
        "code": "a2026fempmc",
        "ids": ",aka2026fempmc,",
        "sources": ",ak,",
        "types": ",origin,phase-data,",
        "nst": 12,
        "dmin": 0.3,
        "rms": 0.5,
        "gap": 97,
        "magType": "ml",
        "type": "earthquake",
        "title": "M 0.9 - 37 km NNE of Chickaloon, Alaska"
      },
      "geometry": {
        "type": "Point",
        "coordinates": [
          -148.157,
          62.099,
          33.8
        ]
      },
      "id": "aka2026fempmc"
    },
    {
      "type": "Feature",
      "properties": {
        "mag": 2.01,
        "place": "73 km NE of Tonopah, Nevada",
        "time": 1773555392911,
        "updated": 1773555556589,
        "tz": null,
        "url": "https://earthquake.usgs.gov/earthquakes/eventpage/nn00912694",
        "detail": "https://earthquake.usgs.gov/earthquakes/feed/v1.0/detail/nn00912694.geojson",
        "felt": null,
        "cdi": null,
        "mmi": null,
        "alert": null,
        "status": "automatic",
        "tsunami": 0,
        "sig": 62,
        "net": "nn",
        "code": "00912694",
        "ids": ",nn00912694,",
        "sources": ",nn,",
        "types": ",origin,phase-data,",
        "nst": 14,
        "dmin": 0.652,
        "rms": 0.2736,
        "gap": 179,
        "magType": "ml",
        "type": "earthquake",
        "title": "M 2.0 - 73 km NE of Tonopah, Nevada"
      },
      "geometry": {
        "type": "Point",
        "coordinates": [
          -116.5678,
          38.4757,
          5.2112
        ]
      },
      "id": "nn00912694"
    }
  ],
  "bbox": [
    -154.253,
    18.043,
    4.1493,
    -66.743333333333,
    62.099,
    33.8
  ]
}
