{
  "type": "FeatureCollection",
  "metadata": {
    "generated": 1756881670000,
    "url": "https://earthquake.usgs.gov/earthquakes/feed/v1.0/summary/all_hour.geojson",
    "title": "USGS All Earthquakes, Past Hour",
    "status": 200,
    "api": "2.2.0",
    "count": 7
  },
  "features": [
    {
      "type": "Feature",
      "properties": {
        "mag": 2.6,
        "place": "7 km NW of Eagle River, Alaska",
        "time": 1756881426432,
        "updated": 1756881525792,
        "tz": null,
        "url": "https://earthquake.usgs.gov/earthquakes/eventpage/ak025baxzx3b",
        "detail": "https://earthquake.usgs.gov/earthquakes/feed/v1.0/detail/ak025baxzx3b.geojson",
        "felt": null,
        "cdi": null,
        "mmi": null,
        "alert": null,
        "status": "automatic",
        "tsunami": 0,
        "sig": 104,
        "net": "ak",
        "code": "025baxzx3b",
        "ids": ",ak025baxzx3b,",
        "sources": ",ak,",
        "types": ",origin,phase-data,",
        "nst": null,
        "dmin": null,
        "rms": 0.44,
        "gap": null,
        "magType": "ml",
        "type": "earthquake",
        "title": "M 2.6 - 7 km NW of Eagle River, Alaska"
      },
      "geometry": {
        "type": "Point",
        "coordinates": [
          -149.6633,
          61.3748,
          30.8
        ]
      },
      "id": "ak025baxzx3b"
    },
    {
      "type": "Feature",
      "properties": {
        "mag": 1.8,
        "place": "18 km E of Balmorhea, Texas",
        "time": 1756880952969,
        "updated": 1756881168229,
        "tz": null,
        "url": "https://earthquake.usgs.gov/earthquakes/eventpage/tx2025rifvau",
        "detail": "https://earthquake.usgs.gov/earthquakes/feed/v1.0/detail/tx2025rifvau.geojson",
        "felt": null,
        "cdi": null,
        "mmi": null,
        "alert": null,
        "status": "automatic",
        "tsunami": 0,
        "sig": 50,
        "net": "tx",
        "code": "2025rifvau",
        "ids": ",tx2025rifvau,",
        "sources": ",tx,",
        "types": ",origin,phase-data,",
        "nst": 19,
        "dmin": 0.1,
        "rms": 0.7,
        "gap": 72,
        "magType": "ml",
        "type": "earthquake",
        "title": "M 1.8 - 18 km E of Balmorhea, Texas"
      },
      "geometry": {
        "type": "Point",
        "coordinates": [
          -103.554,
          31.01,
          5.584
        ]
      },
      "id": "tx2025rifvau"
    },
    {
      "type": "Feature",
      "properties": {
        "mag": 1.7,
        "place": "43 km ESE of Denali National Park, Alaska",
        "time": 1756880809196,
        "updated": 1756881504999,
        "tz": null,
        "url": "https://earthquake.usgs.gov/earthquakes/eventpage/ak025baxxniv",
        "detail": "https://earthquake.usgs.gov/earthquakes/feed/v1.0/detail/ak025baxxniv.geojson",
        "felt": null,
        "cdi": null,
        "mmi": null,
        "alert": null,
        "status": "automatic",
        "tsunami": 0,
        "sig": 44,
        "net": "ak",
        "code": "025baxxniv",
        "ids": ",ak025baxxniv,",
        "sources": ",ak,",
        "types": ",origin,phase-data,",
        "nst": null,
        "dmin": null,
        "rms": 1.44,
        "gap": null,
        "magType": "ml",
        "type": "earthquake",
        "title": "M 1.7 - 43 km ESE of Denali National Park, Alaska"
      },
      "geometry": {
        "type": "Point",
        "coordinates": [
          -150.891,
          63.4295,
          0
        ]
      },
      "id": "ak025baxxniv"
    },
    {
      "type": "Feature",
      "properties": {
        "mag": 0.71,
        "place": "6 km WSW of Anza, CA",
        "time": 1756880519770,
        "updated": 1756880751100,
        "tz": null,
        "url": "https://earthquake.usgs.gov/earthquakes/eventpage/ci41282032",
        "detail": "https://earthquake.usgs.gov/earthquakes/feed/v1.0/detail/ci41282032.geojson",
        "felt": null,
        "cdi": null,
        "mmi": null,
        "alert": null,
        "status": "automatic",
        "tsunami": 0,
        "sig": 8,
        "net": "ci",
        "code": "41282032",
        "ids": ",ci41282032,",
        "sources": ",ci,",
        "types": ",nearby-cities,origin,phase-data,scitech-link,",
        "nst": 44,
        "dmin": 0.03825,
        "rms": 0.16,
        "gap": 32,
        "magType": "ml",
        "type": "earthquake",
        "title": "M 0.7 - 6 km WSW of Anza, CA"
      },
      "geometry": {
        "type": "Point",
        "coordinates": [
          -116.7271667,
          33.528,
          6.05
        ]
      },
      "id": "ci41282032"
    },
    {
      "type": "Feature",
      "properties": {
        "mag": 0.9,
        "place": "38 km WNW of Nikiski, Alaska",
        "time": 1756879932281,
        "updated": 1756880023656,
        "tz": null,
        "url": "https://earthquake.usgs.gov/earthquakes/eventpage/ak025baxukng",
        "detail": "https://earthquake.usgs.gov/earthquakes/feed/v1.0/detail/ak025baxukng.geojson",
        "felt": null,
        "cdi": null,
        "mmi": null,
        "alert": null,
        "status": "automatic",
        "tsunami": 0,
        "sig": 12,
        "net": "ak",
        "code": "025baxukng",
        "ids": ",ak025baxukng,",
        "sources": ",ak,",
        "types": ",origin,phase-data,",
        "nst": null,
        "dmin": null,
        "rms": 0.37,
        "gap": null,
        "magType": "ml",
        "type": "earthquake",
        "title": "M 0.9 - 38 km WNW of Nikiski, Alaska"
      },
      "geometry": {
        "type": "Point",
        "coordinates": [
          -151.9658,
          60.7769,
          202.1
        ]
      },
      "id": "ak025baxukng"
    },
    {
      "type": "Feature",
      "properties": {
        "mag": 0.35,
        "place": "3 km SSW of Mammoth Lakes, CA",
        "time": 1756879477950,
        "updated": 1756880838418,
        "tz": null,
        "url": "https://earthquake.usgs.gov/earthquakes/eventpage/nc75232537",
        "detail": "https://earthquake.usgs.gov/earthquakes/feed/v1.0/detail/nc75232537.geojson",
        "felt": null,
        "cdi": null,
        "mmi": null,
        "alert": null,
        "status": "automatic",
        "tsunami": 0,
        "sig": 2,
        "net": "nc",
        "code": "75232537",
        "ids": ",nc75232537,",
        "sources": ",nc,",
        "types": ",nearby-cities,origin,phase-data,scitech-link,",
        "nst": 6,
        "dmin": 0.02992,
        "rms": 0.01,
        "gap": 166,
        "magType": "md",
        "type": "earthquake",
        "title": "M 0.4 - 3 km SSW of Mammoth Lakes, CA"
      },
      "geometry": {
        "type": "Point",
        "coordinates": [
          -118.984664916992,
          37.6058349609375,
          11.9300003051758
        ]
      },
      "id": "nc75232537"
    },
    {
      "type": "Feature",
      "properties": {
        "mag": 1.4,
        "place": "6 km WNW of Cobb, CA",
        "time": 1756878870510,
        "updated": 1756880240346,
        "tz": null,
        "url": "https://earthquake.usgs.gov/earthquakes/eventpage/nc75232532",
        "detail": "https://earthquake.usgs.gov/earthquakes/feed/v1.0/detail/nc75232532.geojson",
        "felt": null,
        "cdi": null,
        "mmi": null,
        "alert": null,
        "status": "automatic",
        "tsunami": 0,
        "sig": 30,
        "net": "nc",
        "code": "75232532",
        "ids": ",nc75232532,",
        "sources": ",nc,",
        "types": ",nearby-cities,origin,phase-data,scitech-link,",
        "nst": 28,
        "dmin": 0.004149,
        "rms": 0.03,
        "gap": 55,
        "magType": "md",
        "type": "earthquake",
        "title": "M 1.4 - 6 km WNW of Cobb, CA"
      },
      "geometry": {
        "type": "Point",
        "coordinates": [
          -122.794334411621,
          38.8356666564941,
          2.05999994277954
        ]
      },
      "id": "nc75232532"
    }
  ],
  "bbox": [
    -151.9658,
    31.01,
    0,
    -103.554,
    63.4295,
    202.1
  ]
}
