{
  "type": "FeatureCollection",
  "metadata": {
    "generated": 1745390555000,
    "url": "https://earthquake.usgs.gov/earthquakes/feed/v1.0/summary/all_hour.geojson",
    "title": "USGS All Earthquakes, Past Hour",
    "status": 200,
    "api": "1.14.1",
    "count": 7
  },
  "features": [
    {
      "type": "Feature",
      "properties": {
        "mag": 0.9,
        "place": "4 km W of Borrego Springs, CA",
        "time": 1745389172570,
        "updated": 1745389407929,
        "tz": null,
        "url": "https://earthquake.usgs.gov/earthquakes/eventpage/ci40938367",
        "detail": "https://earthquake.usgs.gov/earthquakes/feed/v1.0/detail/ci40938367.geojson",
        "felt": null,
        "cdi": null,
        "mmi": null,
        "alert": null,
        "status": "automatic",
        "tsunami": 0,
        "sig": 12,
        "net": "ci",
        "code": "40938367",
        "ids": ",ci40938367,",
        "sources": ",ci,",
        "types": ",nearby-cities,origin,phase-data,scitech-link,",
        "nst": 49,
        "dmin": 0.08142,
        "rms": 0.21,
        "gap": 60,
        "magType": "ml",
        "type": "earthquake",
        "title": "M 0.9 - 4 km W of Borrego Springs, CA"
      },
      "geometry": {
        "type": "Point",
        "coordinates": [
          -116.4186667,
          33.2575,
          3.15
        ]
      },
      "id": "ci40938367"
    },
    {
      "type": "Feature",
      "properties": {
        "mag": 1.5,
        "place": "59 km WNW of Anderson, Alaska",
        "time": 1745389058111,
        "updated": 1745389187914,
        "tz": null,
        "url": "https://earthquake.usgs.gov/earthquakes/eventpage/ak02556zejjn",
        "detail": "https://earthquake.usgs.gov/earthquakes/feed/v1.0/detail/ak02556zejjn.geojson",
        "felt": null,
        "cdi": null,
        "mmi": null,
        "alert": null,
        "status": "automatic",
        "tsunami": 0,
        "sig": 35,
        "net": "ak",
        "code": "02556zejjn",
        "ids": ",ak02556zejjn,",
        "sources": ",ak,",
        "types": ",origin,phase-data,",
        "nst": null,
        "dmin": null,
        "rms": 1.26,
        "gap": null,
        "magType": "ml",
        "type": "earthquake",
        "title": "M 1.5 - 59 km WNW of Anderson, Alaska"
      },
      "geometry": {
        "type": "Point",
        "coordinates": [
          -150.3904,
          64.461,
          0
        ]
      },
      "id": "ak02556zejjn"
    },
    {
      "type": "Feature",
      "properties": {
        "mag": 0.27,
        "place": "8 km WNW of Cobb, CA",
        "time": 1745388184670,
        "updated": 1745388280628,
        "tz": null,
        "url": "https://earthquake.usgs.gov/earthquakes/eventpage/nc75170141",
        "detail": "https://earthquake.usgs.gov/earthquakes/feed/v1.0/detail/nc75170141.geojson",
        "felt": null,
        "cdi": null,
        "mmi": null,
        "alert": null,
        "status": "automatic",
        "tsunami": 0,
        "sig": 1,
        "net": "nc",
        "code": "75170141",
        "ids": ",nc75170141,",
        "sources": ",nc,",
        "types": ",nearby-cities,origin,phase-data,",
        "nst": 12,
        "dmin": 0.01349,
        "rms": 0.02,
        "gap": 60,
        "magType": "md",
        "type": "earthquake",
        "title": "M 0.3 - 8 km WNW of Cobb, CA"
      },
      "geometry": {
        "type": "Point",
        "coordinates": [
          -122.813331604004,
          38.8366661071777,
          1.78999996185303
        ]
      },
      "id": "nc75170141"
    },
    {
      "type": "Feature",
      "properties": {
        "mag": 0.73,
        "place": "8 km WNW of Cobb, CA",
        "time": 1745388167590,
        "updated": 1745388265304,
        "tz": null,
        "url": "https://earthquake.usgs.gov/earthquakes/eventpage/nc75170136",
        "detail": "https://earthquake.usgs.gov/earthquakes/feed/v1.0/detail/nc75170136.geojson",
        "felt": null,
        "cdi": null,
        "mmi": null,
        "alert": null,
        "status": "automatic",
        "tsunami": 0,
        "sig": 8,
        "net": "nc",
        "code": "75170136",
        "ids": ",nc75170136,",
        "sources": ",nc,",
        "types": ",nearby-cities,origin,phase-data,",
        "nst": 10,
        "dmin": 0.0132,
        "rms": 0.01,
        "gap": 102,
        "magType": "md",
        "type": "earthquake",
        "title": "M 0.7 - 8 km WNW of Cobb, CA"
      },
      "geometry": {
        "type": "Point",
        "coordinates": [
          -122.81233215332,
          38.836498260498,
          1.9099999666214
        ]
      },
      "id": "nc75170136"
    },
    {
      "type": "Feature",
      "properties": {
        "mag": 1.49,
        "place": "7 km NW of The Geysers, CA",
        "time": 1745387856340,
        "updated": 1745387955500,
        "tz": null,
        "url": "https://earthquake.usgs.gov/earthquakes/eventpage/nc75170131",
        "detail": "https://earthquake.usgs.gov/earthquakes/feed/v1.0/detail/nc75170131.geojson",
        "felt": null,
        "cdi": null,
        "mmi": null,
        "alert": null,
        "status": "automatic",
        "tsunami": 0,
        "sig": 34,
        "net": "nc",
        "code": "75170131",
        "ids": ",nc75170131,",
        "sources": ",nc,",
        "types": ",nearby-cities,origin,phase-data,",
        "nst": 32,
        "dmin": 0.01011,
        "rms": 0.03,
        "gap": 47,
        "magType": "md",
        "type": "earthquake",
        "title": "M 1.5 - 7 km NW of The Geysers, CA"
      },
      "geometry": {
        "type": "Point",
        "coordinates": [
          -122.821830749512,
          38.8191680908203,
          2.38000011444092
        ]
      },
      "id": "nc75170131"
    },
    {
      "type": "Feature",
      "properties": {
        "mag": 1.12,
        "place": "3 km SSE of The Geysers, CA",
        "time": 1745387755430,
        "updated": 1745390236818,
        "tz": null,
        "url": "https://earthquake.usgs.gov/earthquakes/eventpage/nc75170126",
        "detail": "https://earthquake.usgs.gov/earthquakes/feed/v1.0/detail/nc75170126.geojson",
        "felt": null,
        "cdi": null,
        "mmi": null,
        "alert": null,
        "status": "automatic",
        "tsunami": 0,
        "sig": 19,
        "net": "nc",
        "code": "75170126",
        "ids": ",nc75170126,",
        "sources": ",nc,",
        "types": ",nearby-cities,origin,phase-data,scitech-link,",
        "nst": 8,
        "dmin": 0.008214,
        "rms": 0.02,
        "gap": 122,
        "magType": "md",
        "type": "earthquake",
        "title": "M 1.1 - 3 km SSE of The Geysers, CA"
      },
      "geometry": {
        "type": "Point",
        "coordinates": [
          -122.737998962402,
          38.7591667175293,
          0.939999997615814
        ]
      },
      "id": "nc75170126"
    },
    {
      "type": "Feature",
      "properties": {
        "mag": 2.2,
        "place": "21 km WNW of Salamatof, Alaska",
        "time": 1745387446877,
        "updated": 1745387555319,
        "tz": null,
        "url": "https://earthquake.usgs.gov/earthquakes/eventpage/ak02556z078v",
        "detail": "https://earthquake.usgs.gov/earthquakes/feed/v1.0/detail/ak02556z078v.geojson",
        "felt": null,
        "cdi": null,
        "mmi": null,
        "alert": null,
        "status": "automatic",
        "tsunami": 0,
        "sig": 74,
        "net": "ak",
        "code": "02556z078v",
        "ids": ",ak02556z078v,",
        "sources": ",ak,",
        "types": ",origin,phase-data,",
        "nst": null,
        "dmin": null,
        "rms": 0.41,
        "gap": null,
        "magType": "ml",
        "type": "earthquake",
        "title": "M 2.2 - 21 km WNW of Salamatof, Alaska"
      },
      "geometry": {
        "type": "Point",
        "coordinates": [
          -151.7045,
          60.6594,
          73.7
        ]
      },
      "id": "ak02556z078v"
    }
  ],
  "bbox": [
    -151.7045,
    33.2575,
    0,
    -116.4186667,
    64.461,
    73.7
  ]
}
