{
  "type": "FeatureCollection",
  "metadata": {
    "generated": 1758091410000,
    "url": "https://earthquake.usgs.gov/earthquakes/feed/v1.0/summary/all_hour.geojson",
    "title": "USGS All Earthquakes, Past Hour",
    "status": 200,
    "api": "2.2.0",
    "count": 5
  },
  "features": [
    {
      "type": "Feature",
      "properties": {
        "mag": 4.7,
        "place": "96 km SE of Old Harbor, Alaska",
        "time": 1758090938805,
        "updated": 1758091236687,
        "tz": null,
        "url": "https://earthquake.usgs.gov/earthquakes/eventpage/ak025by3iekl",
        "detail": "https://earthquake.usgs.gov/earthquakes/feed/v1.0/detail/ak025by3iekl.geojson",
        "felt": null,
        "cdi": null,
        "mmi": null,
        "alert": null,
        "status": "automatic",
        "tsunami": 1,
        "sig": 340,
        "net": "ak",
        "code": "025by3iekl",
        "ids": ",at00t2pznb,ak025by3iekl,",
        "sources": ",at,ak,",
        "types": ",impact-link,origin,phase-data,",
        "nst": null,
        "dmin": null,
        "rms": 0.87,
        "gap": null,
        "magType": "ml",
        "type": "earthquake",
        "title": "M 4.7 - 96 km SE of Old Harbor, Alaska"
      },
      "geometry": {
        "type": "Point",
        "coordinates": [
          -152.1292,
          56.6187,
          0
        ]
      },
      "id": "ak025by3iekl"
    },
    {
      "type": "Feature",
      "properties": {
        "mag": 0.55,
        "place": "20 km ESE of Little Lake, CA",
        "time": 1758089407030,
        "updated": 1758089617724,
        "tz": null,
        "url": "https://earthquake.usgs.gov/earthquakes/eventpage/ci41292816",
        "detail": "https://earthquake.usgs.gov/earthquakes/feed/v1.0/detail/ci41292816.geojson",
        "felt": null,
        "cdi": null,
        "mmi": null,
        "alert": null,
        "status": "automatic",
        "tsunami": 0,
        "sig": 5,
        "net": "ci",
        "code": "41292816",
        "ids": ",ci41292816,",
        "sources": ",ci,",
        "types": ",nearby-cities,origin,phase-data,scitech-link,",
        "nst": 15,
        "dmin": 0.0575,
        "rms": 0.1,
        "gap": 88,
        "magType": "ml",
        "type": "earthquake",
        "title": "M 0.6 - 20 km ESE of Little Lake, CA"
      },
      "geometry": {
        "type": "Point",
        "coordinates": [
          -117.6888333,
          35.8995,
          3.29
        ]
      },
      "id": "ci41292816"
    },
    {
      "type": "Feature",
      "properties": {
        "mag": 0.88,
        "place": "10 km E of Ocotillo Wells, CA",
        "time": 1758088754150,
        "updated": 1758088966388,
        "tz": null,
        "url": "https://earthquake.usgs.gov/earthquakes/eventpage/ci41292808",
        "detail": "https://earthquake.usgs.gov/earthquakes/feed/v1.0/detail/ci41292808.geojson",
        "felt": null,
        "cdi": null,
        "mmi": null,
        "alert": null,
        "status": "automatic",
        "tsunami": 0,
        "sig": 12,
        "net": "ci",
        "code": "41292808",
        "ids": ",ci41292808,",
        "sources": ",ci,",
        "types": ",nearby-cities,origin,phase-data,scitech-link,",
        "nst": 39,
        "dmin": 0.05805,
        "rms": 0.23,
        "gap": 50,
        "magType": "ml",
        "type": "earthquake",
        "title": "M 0.9 - 10 km E of Ocotillo Wells, CA"
      },
      "geometry": {
        "type": "Point",
        "coordinates": [
          -116.0256667,
          33.1315,
          8.01
        ]
      },
      "id": "ci41292808"
    },
    {
      "type": "Feature",
      "properties": {
        "mag": 0.52,
        "place": "13 km SW of Searles Valley, CA",
        "time": 1758088422960,
        "updated": 1758088631909,
        "tz": null,
        "url": "https://earthquake.usgs.gov/earthquakes/eventpage/ci41292800",
        "detail": "https://earthquake.usgs.gov/earthquakes/feed/v1.0/detail/ci41292800.geojson",
        "felt": null,
        "cdi": null,
        "mmi": null,
        "alert": null,
        "status": "automatic",
        "tsunami": 0,
        "sig": 4,
        "net": "ci",
        "code": "41292800",
        "ids": ",ci41292800,",
        "sources": ",ci,",
        "types": ",nearby-cities,origin,phase-data,scitech-link,",
        "nst": 25,
        "dmin": 0.08251,
        "rms": 0.15,
        "gap": 68,
        "magType": "ml",
        "type": "earthquake",
        "title": "M 0.5 - 13 km SW of Searles Valley, CA"
      },
      "geometry": {
        "type": "Point",
        "coordinates": [
          -117.5163333,
          35.6986667,
          4.48
        ]
      },
      "id": "ci41292800"
    },
    {
      "type": "Feature",
      "properties": {
        "mag": 2.9,
        "place": "33 km WNW of Willow, Alaska",
        "time": 1758087915091,
        "updated": 1758088030058,
        "tz": null,
        "url": "https://earthquake.usgs.gov/earthquakes/eventpage/ak025by2z2td",
        "detail": "https://earthquake.usgs.gov/earthquakes/feed/v1.0/detail/ak025by2z2td.geojson",
        "felt": null,
        "cdi": null,
        "mmi": null,
        "alert": null,
        "status": "automatic",
        "tsunami": 0,
        "sig": 129,
        "net": "ak",
        "code": "025by2z2td",
        "ids": ",ak025by2z2td,",
        "sources": ",ak,",
        "types": ",origin,phase-data,",
        "nst": null,
        "dmin": null,
        "rms": 0.47,
        "gap": null,
        "magType": "ml",
        "type": "earthquake",
        "title": "M 2.9 - 33 km WNW of Willow, Alaska"
      },
      "geometry": {
        "type": "Point",
        "coordinates": [
          -150.5814,
          61.9076,
          0.8
        ]
      },
      "id": "ak025by2z2td"
    }
  ],
  "bbox": [
    -152.1292,
    33.1315,
    0,
    -116.0256667,
    61.9076,
    8.01
  ]
}
